lsttools/__init__.py
lsttools/flatten.py
lsttools-0.0.2.dist-info/LICENSE
lsttools-0.0.2.dist-info/METADATA
lsttools-0.0.2.dist-info/WHEEL
lsttools-0.0.2.dist-info/top_level.txt
lsttools-0.0.2.dist-info/RECORD
