Metadata-Version: 2.1
Name: lsttools
Version: 0.0.2
Summary: Package for manipulating lists
Home-page: https://gitlab.com/b2326/listtools
Author: Ben Larisch
Author-email: benlarisch2019@gmail.com
License: UNKNOWN
Project-URL: Bug Tracker, https://gitlab.com/b2326/listtools/-/issues
Platform: UNKNOWN
Classifier: Programming Language :: Python :: 3
Classifier: License :: OSI Approved :: MIT License
Classifier: Operating System :: OS Independent
Requires-Python: >=3.6
License-File: LICENSE
